comwatt_client/__init__.py
comwatt_client/client.py
comwatt_client-0.2.3.dist-info/METADATA
comwatt_client-0.2.3.dist-info/WHEEL
comwatt_client-0.2.3.dist-info/top_level.txt
comwatt_client-0.2.3.dist-info/RECORD
